MANIFEST.in
requirements.txt
setup.py
docs/source/conf.py
env/runtime/bin/django-admin.py
env/testing/bin/django-admin.py
examples/polls/__init__.py
examples/polls/settings.py
examples/polls/urls.py
unimatrix.ext.django.egg-info/PKG-INFO
unimatrix.ext.django.egg-info/SOURCES.txt
unimatrix.ext.django.egg-info/dependency_links.txt
unimatrix.ext.django.egg-info/requires.txt
unimatrix.ext.django.egg-info/top_level.txt
unimatrix/ext/django/VERSION
unimatrix/ext/django/__init__.py
unimatrix/ext/django/apps.py
unimatrix/ext/django/asgi.py
unimatrix/ext/django/celery.py
unimatrix/ext/django/wsgi.py
unimatrix/ext/django/lib/__init__.py
unimatrix/ext/django/lib/middleware.py
unimatrix/ext/django/lib/etc/__init__.py
unimatrix/ext/django/management/commands/__init__.py
unimatrix/ext/django/management/commands/awaitservices.py
unimatrix/ext/django/services/__init__.py
unimatrix/ext/django/services/email.py
unimatrix/ext/django/services/template.py
unimatrix/ext/django/settings/__init__.py
unimatrix/ext/django/settings/build.py
unimatrix/ext/django/settings/const.py
unimatrix/ext/django/settings/email.py
unimatrix/ext/django/settings/http.py
unimatrix/ext/django/settings/logging.py
unimatrix/ext/django/settings/rdbms.py
unimatrix/ext/django/settings/runtime.py
unimatrix/ext/django/tests/__init__.py
unimatrix/ext/django/tests/test_rdbms_configuration.py
unimatrix/ext/django/urls/__init__.py
unimatrix/ext/django/urls/runtime.py