Metadata-Version: 1.1
Name: unimatrix.ext.django
Version: 0.1.41
Summary: Unimatrix One Django Library
Home-page: https://gitlab.com/unimatrixone/libraries/python-unimatrix
Author: Cochise Ruhulessin
Author-email: cochise.ruhulessin@digitalcitizen.nl
License: GPLv3
Platform: UNKNOWN
Classifier: Development Status :: 4 - Beta
Classifier: Framework :: Django
Classifier: Intended Audience :: Developers
Classifier: License :: OSI Approved :: GNU General Public License (GPL)
Classifier: License :: OSI Approved :: GNU General Public License v3 (GPLv3)
Classifier: Operating System :: POSIX
Classifier: Operating System :: POSIX :: Linux
Classifier: Programming Language :: Python :: 3.5
Classifier: Programming Language :: Python :: 3.6
Classifier: Programming Language :: Python :: 3.7
Classifier: Programming Language :: Python :: 3.8
Classifier: Programming Language :: Python :: 3 :: Only
Classifier: Topic :: Software Development :: Libraries
Classifier: Topic :: System :: Clustering
Classifier: Topic :: System :: Distributed Computing
